exabel_data_sdk/__init__.py
exabel_data_sdk/client/__init__.py
exabel_data_sdk/client/client_config.py
exabel_data_sdk/client/exabel_client.py
exabel_data_sdk/client/user_login.py
exabel_data_sdk/client/api/__init__.py
exabel_data_sdk/client/api/bulk_import.py
exabel_data_sdk/client/api/bulk_insert.py
exabel_data_sdk/client/api/data_set_api.py
exabel_data_sdk/client/api/derived_signal_api.py
exabel_data_sdk/client/api/entity_api.py
exabel_data_sdk/client/api/error_handler.py
exabel_data_sdk/client/api/export_api.py
exabel_data_sdk/client/api/kpi_api.py
exabel_data_sdk/client/api/library_api.py
exabel_data_sdk/client/api/namespace_api.py
exabel_data_sdk/client/api/pageable_resource.py
exabel_data_sdk/client/api/prediction_model_api.py
exabel_data_sdk/client/api/proto_utils.py
exabel_data_sdk/client/api/relationship_api.py
exabel_data_sdk/client/api/resource_creation_result.py
exabel_data_sdk/client/api/search_service.py
exabel_data_sdk/client/api/signal_api.py
exabel_data_sdk/client/api/tag_api.py
exabel_data_sdk/client/api/time_series_api.py
exabel_data_sdk/client/api/user_api.py
exabel_data_sdk/client/api/api_client/__init__.py
exabel_data_sdk/client/api/api_client/data_set_api_client.py
exabel_data_sdk/client/api/api_client/derived_signal_api_client.py
exabel_data_sdk/client/api/api_client/entity_api_client.py
exabel_data_sdk/client/api/api_client/exabel_api_group.py
exabel_data_sdk/client/api/api_client/kpi_api_client.py
exabel_data_sdk/client/api/api_client/library_api_client.py
exabel_data_sdk/client/api/api_client/namespace_api_client.py
exabel_data_sdk/client/api/api_client/prediction_model_api_client.py
exabel_data_sdk/client/api/api_client/relationship_api_client.py
exabel_data_sdk/client/api/api_client/signal_api_client.py
exabel_data_sdk/client/api/api_client/tag_api_client.py
exabel_data_sdk/client/api/api_client/time_series_api_client.py
exabel_data_sdk/client/api/api_client/user_api_client.py
exabel_data_sdk/client/api/api_client/grpc/__init__.py
exabel_data_sdk-6.3.0.dist-info/licenses/LICENSE
exabel_data_sdk-6.3.0.dist-info/METADATA
exabel_data_sdk-6.3.0.dist-info/WHEEL
exabel_data_sdk-6.3.0.dist-info/top_level.txt
exabel_data_sdk-6.3.0.dist-info/RECORD
