Metadata-Version: 2.4
Name: exabel-data-sdk
Version: 6.3.0
Summary: Python SDK for the Exabel Data API
Home-page: https://github.com/Exabel/python-sdk
Author: Exabel
Author-email: support@exabel.com
License: MIT
Classifier: Development Status :: 5 - Production/Stable
Classifier: Intended Audience :: Financial and Insurance Industry
Classifier: Programming Language :: Python :: 3.9
Classifier: Programming Language :: Python :: 3.10
Classifier: Programming Language :: Python :: 3.11
Classifier: Programming Language :: Python :: 3.12
Classifier: Programming Language :: Python :: 3.13
Classifier: License :: OSI Approved :: MIT License
Classifier: Operating System :: OS Independent
Requires-Python: >=3.9
License-File: LICENSE
Requires-Dist: google-api-core>1.31.3
Requires-Dist: googleapis-common-protos>=1.56.0
Requires-Dist: grpcio
Requires-Dist: openpyxl
Requires-Dist: pandas
Requires-Dist: protobuf>=4
Requires-Dist: requests
Requires-Dist: tqdm
Provides-Extra: snowflake
Requires-Dist: sqlalchemy; extra == "snowflake"
Requires-Dist: snowflake-connector-python[pandas]; extra == "snowflake"
Requires-Dist: snowflake-sqlalchemy; extra == "snowflake"
Provides-Extra: bigquery
Requires-Dist: google-cloud-bigquery; extra == "bigquery"
Requires-Dist: sqlalchemy-bigquery; extra == "bigquery"
Provides-Extra: athena
Requires-Dist: sqlalchemy; extra == "athena"
Requires-Dist: pyathena; extra == "athena"
Requires-Dist: pyarrow; extra == "athena"
Provides-Extra: all
Requires-Dist: sqlalchemy; extra == "all"
Requires-Dist: snowflake-connector-python[pandas]; extra == "all"
Requires-Dist: snowflake-sqlalchemy; extra == "all"
Requires-Dist: google-cloud-bigquery; extra == "all"
Requires-Dist: sqlalchemy-bigquery; extra == "all"
Requires-Dist: sqlalchemy; extra == "all"
Requires-Dist: pyathena; extra == "all"
Requires-Dist: pyarrow; extra == "all"
Dynamic: author
Dynamic: author-email
Dynamic: classifier
Dynamic: description
Dynamic: description-content-type
Dynamic: home-page
Dynamic: license
Dynamic: license-file
Dynamic: provides-extra
Dynamic: requires-dist
Dynamic: requires-python
Dynamic: summary
